{
    "name":  "RoadLens Scout",
    "version":  "0.1.9",
    "generatedAt":  "2026-06-24T13:10:19Z",
    "apk":  {
                "path":  "https://github.com/Its-ze/roadlens-scout/releases/download/v0.1.9/roadlens-scout-v0.1.9-debug.apk",
                "asset":  "roadlens-scout-v0.1.9-debug.apk",
                "bytes":  5445681,
                "sha256":  "4852a9cf54d8976f1ce11010bab1d7f7576fe2196f4531048b2fc684f23d9bd8"
            },
    "firmware":  {
                     "manifest":  "flasher/manifest.json",
                     "path":  "flasher/firmware/esp32/firmware.bin",
                     "bytes":  1191808,
                     "sha256":  "12612690d173ecce290cf6930078836cd9106e3d8b8e83dbe0a886682155514a",
                     "builds":  [
                                    {
                                        "chipFamily":  "ESP32",
                                        "path":  "flasher/firmware/esp32/firmware.bin",
                                        "bytes":  1191808,
                                        "sha256":  "12612690d173ecce290cf6930078836cd9106e3d8b8e83dbe0a886682155514a"
                                    },
                                    {
                                        "chipFamily":  "ESP32-S3",
                                        "path":  "flasher/firmware/esp32s3/firmware.bin",
                                        "bytes":  1070016,
                                        "sha256":  "bf7aa393ae956dbe09b9965cfca96fb67088d81755dc75cf2ea1ca6c06b76caa"
                                    },
                                    {
                                        "chipFamily":  "ESP32-C3",
                                        "path":  "flasher/firmware/esp32c3/firmware.bin",
                                        "bytes":  1153840,
                                        "sha256":  "d28f8f2344d16fd76c350704ec5603e888e25f85bffb27b6f5d5d1a45c9d2bef"
                                    }
                                ]
                 },
    "signatures":  {
                       "path":  "signatures.json",
                       "version":  "2026.06.24.209126de",
                       "bytes":  16540,
                       "sha256":  "4aef8033e7e084a45c960ba58d3312e97d69e9c368df772f6bd5e0732a8a964c",
                       "wifiPrefixes":  42,
                       "blePrefixes":  42,
                       "bleNamePatterns":  4,
                       "bleManufacturerIds":  1,
                       "ravenServiceUuids":  8
                   }
}
